edx_proctoring_proctortrack/__init__.py
edx_proctoring_proctortrack/backends/__init__.py
edx_proctoring_proctortrack/backends/proctortrack_rest.py
edx_proctoring_proctortrack/static/proctortrack_custom.js
edx_proctoring_proctortrack-1.2.1.dist-info/AUTHORS
edx_proctoring_proctortrack-1.2.1.dist-info/LICENSE.md
edx_proctoring_proctortrack-1.2.1.dist-info/METADATA
edx_proctoring_proctortrack-1.2.1.dist-info/WHEEL
edx_proctoring_proctortrack-1.2.1.dist-info/entry_points.txt
edx_proctoring_proctortrack-1.2.1.dist-info/top_level.txt
edx_proctoring_proctortrack-1.2.1.dist-info/RECORD
