Metadata-Version: 2.1
Name: edx-proctoring-proctortrack
Version: 1.2.1
Summary: Proctoring subsystem for edX-proctoring
Home-page: https://github.com/joshivj/edx-proctoring-proctortrack
Author: Verificient
Author-email: vivek@verificient.com
License: Apache-2.0
Keywords: Proctortrack edx
Platform: UNKNOWN
Classifier: Programming Language :: Python
Classifier: Programming Language :: Python :: 2
Classifier: Programming Language :: Python :: 2.7
Classifier: Programming Language :: Python :: 3
Classifier: Programming Language :: Python :: 3.5
Classifier: Programming Language :: Python :: 3.6
Classifier: Programming Language :: Python :: 3.7
Classifier: Programming Language :: Python :: Implementation :: CPython
Requires-Dist: edx-proctoring
